llm_gigachat.py
llm_gigachat-0.1.dist-info/LICENSE
llm_gigachat-0.1.dist-info/METADATA
llm_gigachat-0.1.dist-info/WHEEL
llm_gigachat-0.1.dist-info/entry_points.txt
llm_gigachat-0.1.dist-info/top_level.txt
llm_gigachat-0.1.dist-info/RECORD
