Metadata-Version: 2.1
Name: llm-gigachat
Version: 0.1
Author: l3g5
License: Apache-2.0
Project-URL: Homepage, https://github.com/L3G5/llm-gigachat
Project-URL: Issues, https://github.com/L3G5/llm-gigachat/issues
Classifier: License :: OSI Approved :: Apache Software License
Requires-Python: >3.7
License-File: LICENSE
Requires-Dist: llm
Requires-Dist: requests
Requires-Dist: pydantic
